LICENSE
MANIFEST.in
README.rst
requirements.txt
setup.cfg
setup.py
bin/mid3cover
bin/mid3generate.py
bin/mid3ls
mutagenerate/__init__.py
mutagenerate/amazon.py
mutagenerate/core.py
mutagenerate/log.py
mutagenerate/musicbrainz.py
mutagenerate/source.py
mutagenerate/tests.py
mutagenerate/util.py
mutagenerate.egg-info/PKG-INFO
mutagenerate.egg-info/SOURCES.txt
mutagenerate.egg-info/dependency_links.txt
mutagenerate.egg-info/requires.txt
mutagenerate.egg-info/top_level.txt