Metadata-Version: 1.0
Name: mutagenerate
Version: 0.3.0
Summary: Mutagenerate is a python module which tries to extend as much as possible id3 tags based on tags already set and public web resources
Home-page: https://github.com/gtnx/mutagenerate
Author: Guillaume Thomas
Author-email: guillaume.thomas642@gmail.com
License: LICENCE.txt
Platform: UNKNOWN
